biblechichewa/__init__.py
biblechichewa/main.py
biblechichewa/content/books.json
biblechichewa/resources/1/1.json
biblechichewa/resources/1/10.json
biblechichewa/resources/1/11.json
biblechichewa/resources/1/12.json
biblechichewa/resources/1/13.json
biblechichewa/resources/1/14.json
biblechichewa/resources/1/15.json
biblechichewa/resources/1/16.json
biblechichewa/resources/1/17.json
biblechichewa/resources/1/18.json
biblechichewa/resources/1/19.json
biblechichewa/resources/1/2.json
biblechichewa/resources/1/20.json
biblechichewa/resources/1/21.json
biblechichewa/resources/1/22.json
biblechichewa/resources/1/23.json
biblechichewa/resources/1/24.json
biblechichewa/resources/1/25.json
biblechichewa/resources/1/26.json
biblechichewa/resources/1/27.json
biblechichewa/resources/1/28.json
biblechichewa/resources/1/29.json
biblechichewa/resources/1/3.json
biblechichewa/resources/1/30.json
biblechichewa/resources/1/31.json
biblechichewa/resources/1/32.json
biblechichewa/resources/1/33.json
biblechichewa/resources/1/34.json
biblechichewa/resources/1/35.json
biblechichewa/resources/1/36.json
biblechichewa/resources/1/37.json
biblechichewa/resources/1/38.json
biblechichewa/resources/1/39.json
biblechichewa/resources/1/4.json
biblechichewa/resources/1/40.json
biblechichewa/resources/1/41.json
biblechichewa/resources/1/42.json
biblechichewa/resources/1/43.json
biblechichewa/resources/1/44.json
biblechichewa/resources/1/45.json
biblechichewa/resources/1/46.json
biblechichewa/resources/1/47.json
biblechichewa/resources/1/48.json
biblechichewa/resources/1/49.json
biblechichewa/resources/1/5.json
biblechichewa/resources/1/50.json
biblechichewa/resources/1/6.json
biblechichewa/resources/1/7.json
biblechichewa/resources/1/8.json
biblechichewa/resources/1/9.json
biblechichewa/resources/10/1.json
biblechichewa/resources/10/10.json
biblechichewa/resources/10/11.json
biblechichewa/resources/10/12.json
biblechichewa/resources/10/13.json
biblechichewa/resources/10/14.json
bible_chichewa-1.0.7.dist-info/METADATA
bible_chichewa-1.0.7.dist-info/WHEEL
bible_chichewa-1.0.7.dist-info/licenses/LICENSE
bible_chichewa-1.0.7.dist-info/RECORD
