Metadata-Version: 2.4
Name: bible-chichewa
Version: 1.0.7
Summary:  Access and integrate the Chichewa translation of the Bible into your python applications with ease
Project-URL: Homepage, https://github.com/AllBible/bible-chichewa-py
Project-URL: Issues, https://github.com/AllBible/bible-chichewa-py
Author-email: M2K Developments <m2kdevelopments@gmail.com>
License-File: LICENSE
Classifier: License :: OSI Approved :: MIT License
Classifier: Operating System :: OS Independent
Classifier: Programming Language :: Python :: 3
Requires-Python: >=3.0
